assignment2/counter/counter.v
module counter(
	output q0,q1,q2,T0,T1,T2,
	input clk
	);

wire clk;
reg q0,q1,q2,T0,T1,T2;

initial begin
	q0 = 0;
	q1 = 0;
	q2 = 0;
	T0 = 0;
	T1 = 0;
	T2 = 0;
end

always begin
	if(q0 == 1 & q1 ==1 & q2 == 1)
	begin
		q0 = 0;
		q1 = 0;
		q2 = 0;
	end
	#5;
end

always @(posedge clk)
begin
	T0 = (~q0 & q1 & q2);
	T1 = q2;
	T2 = 1;

	q0 <= (T0 ^ q0);
	q1 <= (T1 ^ q1);
	q2 <= (T2 ^ q2);
end
endmodule

assignment2/tb_counter.v
module tb_counter();

reg clk;
wire q0,q1,q2,T0,T1,T2;

initial begin
	$dumpfile("counter.vcd");
	$dumpvars(0,tb_counter);
	$monitor("%g\t %b %b %b ",$time,q0,q1,q2);
	clk = 0;
	#200 $finish;
end

always begin
	#5 clk <= ~clk;
end

counter upcounter(q0,q1,q2,T0,T1,T2,clk);

endmodule

assignment2/counter.vcd
$date
	Tue Mar  8 10:51:57 2016
$end
$version
	Icarus Verilog
$end
$timescale
	1s
$end
$scope module tb_counter $end
$var wire 1 ! T0 $end
$var wire 1 " T1 $end
$var wire 1 # T2 $end
$var wire 1 $ q0 $end
$var wire 1 % q1 $end
$var wire 1 & q2 $end
$var reg 1 ' clk $end
$scope module upcounter $end
$var wire 1 ( clk $end
$var reg 1 ) T0 $end
$var reg 1 * T1 $end
$var reg 1 + T2 $end
$var reg 1 , q0 $end
$var reg 1 - q1 $end
$var reg 1 . q2 $end
$upscope $end
$upscope $end
$enddefinitions $end
#0
$dumpvars
0.
0-
0,
0+
0*
0)
0(
0'
0&
0%
0$
0#
0"
0!
$end
#5
1.
1&
1+
1#
1'
1(
#10
0'
0(
#15
0.
0&
1-
1%
1*
1"
1'
1(
#20
0'
0(
#25
1.
1&
0*
0"
1'
1(
#30
0'
0(
#35
0.
0&
0-
0%
1,
1$
1*
1"
1)
1!
1'
1(
#40
0'
0(
#45
1.
1&
0*
0"
0)
0!
1'
1(
#50
0'
0(
#55
0.
0&
1-
1%
1*
1"
1'
1(
#60
0'
0(
#65
1.
1&
0*
0"
1'
1(
#70
0'
0(
0.
0&
0-
0%
0,
0$
#75
1.
1&
1'
1(
#80
0'
0(
#85
0.
0&
1-
1%
1*
1"
1'
1(
#90
0'
0(
#95
1.
1&
0*
0"
1'
1(
#100
0'
0(
#105
0.
0&
0-
0%
1,
1$
1*
1"
1)
1!
1'
1(
#110
0'
0(
#115
1.
1&
0*
0"
0)
0!
1'
1(
#120
0'
0(
#125
0.
0&
1-
1%
1*
1"
1'
1(
#130
0'
0(
#135
1.
1&
0*
0"
1'
1(
#140
0'
0(
0.
0&
0-
0%
0,
0$
#145
1.
1&
1'
1(
#150
0'
0(
#155
0.
0&
1-
1%
1*
1"
1'
1(
#160
0'
0(
#165
1.
1&
0*
0"
1'
1(
#170
0'
0(
#175
0.
0&
0-
0%
1,
1$
1*
1"
1)
1!
1'
1(
#180
0'
0(
#185
1.
1&
0*
0"
0)
0!
1'
1(
#190
0'
0(
#195
0.
0&
1-
1%
1*
1"
1'
1(
