final-exam/demux/demux.v
module demux(X,sel1,sel2,A,B,C,D);
input X,sel1,sel2;
output A,B,C,D;

assign A = X & ~sel1 & ~sel2;
assign B = X & ~sel1 & sel2;
assign C = X & sel1 & ~sel2;
assign D = X & sel1 & sel2;

endmodule

assignments/demux/demux_tb.v
module demux_tb();
reg X,sel1,sel2;
wire A,B,C,D;

demux uut(
	.X(X),
	.sel1(sel1),
	.sel2(sel2),
	.A(A),
	.B(B),
	.C(C),
	.D(D)
	);

initial begin
	X = 0; sel1 = 0; sel2 = 0;
	#10 X=1'b0; sel1=1'b0; sel2 = 1'b1;
	#10 X=1'b0; sel1=1'b1; sel2 = 1'b0;
	#10 X=1'b0; sel1=1'b1; sel2 = 1'b1;
	#10 X=1'b1; sel1=1'b0; sel2 = 1'b0;
	#10 X=1'b1; sel1=1'b0; sel2 = 1'b1;
	#10 X=1'b1; sel1=1'b1; sel2 = 1'b0;
	#10 X=1'b1; sel1=1'b1; sel2 = 1'b1;
    #10 $finish;
end

initial begin
	$dumpfile("demux.vcd");
	$dumpvars;
end

endmodule

assignments/demux/demux.vcd
$date
	Mon Apr 11 22:50:08 2016
$end
$version
	Icarus Verilog
$end
$timescale
	1s
$end
$scope module demux_tb $end
$var wire 1 ! A $end
$var wire 1 " B $end
$var wire 1 # C $end
$var wire 1 $ D $end
$var reg 1 % X $end
$var reg 1 & sel1 $end
$var reg 1 ' sel2 $end
$scope module uut $end
$var wire 1 ! A $end
$var wire 1 " B $end
$var wire 1 # C $end
$var wire 1 $ D $end
$var wire 1 ( X $end
$var wire 1 ) sel1 $end
$var wire 1 * sel2 $end
$upscope $end
$upscope $end
$enddefinitions $end
#0
$dumpvars
0*
0)
0(
0'
0&
0%
0$
0#
0"
0!
$end
#10
1'
1*
#20
0'
0*
1&
1)
#30
1'
1*
#40
1!
0'
0*
0&
0)
1%
1(
#50
0!
1"
1'
1*
#60
1#
0"
0'
0*
1&
1)
#70
0#
1$
1'
1*
