assignments/pseudorandomnumbergen/pseudo.v
module pseudo(clk,a0,a1,a2,a3);
input clk;
output a0,a1,a2,a3;

wire w1;
xor G1(w1,a2,a3);

DFF D1(w1,clk,a0);
DFF D2(a0,clk,a1);
DFF D3(a1,clk,a2);
DFF D4(a2,clk,a3);

endmodule

module DFF(data,clk,q);
input data,clk;
output reg q;

initial begin
	q = 1'b1;
end

always@(posedge clk) begin
	q <= data;
end
endmodule

assignments/pseudorandomnumbergen/pseudo_tb.v
module pseudo_tb();
reg clk;
wire a0,a1,a2,a3;

pseudo uut(
	.clk(clk),
	.a0(a0),
	.a1(a1),
	.a2(a2),
	.a3(a3)
	);

initial begin
	clk = 0;
	#10 clk = ~clk;
	#10 clk = ~clk;
	#10 clk = ~clk;
	#10 clk = ~clk;
	#10 clk = ~clk;
	#10 clk = ~clk;
	#10 clk = ~clk;
	#10 clk = ~clk;
	#10 clk = ~clk;
	#10 clk = ~clk;
	#10 clk = ~clk;
	#10 clk = ~clk;
	#10 clk = ~clk;
	#10 clk = ~clk;
	#10 clk = ~clk;
	#10 clk = ~clk;
	#10 clk = ~clk;
	#10 clk = ~clk;
	#10 clk = ~clk;
	#10 clk = ~clk;
	#10 clk = ~clk;
	#10 clk = ~clk;
	#10 clk = ~clk;
	#10 clk = ~clk;
	#10 clk = ~clk;
	#10 clk = ~clk;
	#10 clk = ~clk;
	#10 clk = ~clk;
	#10 clk = ~clk;
	#10 clk = ~clk;
	#10 clk = ~clk;
	#10 clk = ~clk;
	#10 clk = ~clk;
	#10 clk = ~clk;
	#10 clk = ~clk;
	#10 clk = ~clk;
	#10 clk = ~clk;
	#10 clk = ~clk;
	#10 clk = ~clk;
	#10 clk = ~clk;
	#10 clk = ~clk;
	#10 clk = ~clk;
	#10 clk = ~clk;
	#10 clk = ~clk;
	#10 clk = ~clk;
	#10 clk = ~clk;
	#10 clk = ~clk;
	#10 clk = ~clk;
	#10 clk = ~clk;
	#10 clk = ~clk;
	#10 clk = ~clk;
	#10 clk = ~clk;
	#10 clk = ~clk;
	#10 clk = ~clk;
	#10 clk = ~clk;
	#10 clk = ~clk;
	#10 clk = ~clk;
	#10 clk = ~clk;
	#10 clk = ~clk;
	#10 clk = ~clk;
	#10 clk = ~clk;
	#10 clk = ~clk;
	#10 clk = ~clk;
	#10 clk = ~clk;
	#10 clk = ~clk;
	#10 clk = ~clk;
	#10 clk = ~clk;
	#10 clk = ~clk;
	#10 clk = ~clk;
	#10 clk = ~clk;
	#10 clk = ~clk;
	#10 clk = ~clk;
	#10 clk = ~clk;
	#10 clk = ~clk;
	#10 clk = ~clk;
	#10 clk = ~clk;
	#10 clk = ~clk;
	#10 clk = ~clk;
	#10 $finish;
end

initial begin
	$dumpfile("test.vcd");
	$dumpvars;
end

endmodule

assignments/pseudorandomnumbergen/test.vcd
$date
	Tue Apr 12 01:06:59 2016
$end
$version
	Icarus Verilog
$end
$timescale
	1s
$end
$scope module pseudo_tb $end
$var wire 1 ! a0 $end
$var wire 1 " a1 $end
$var wire 1 # a2 $end
$var wire 1 $ a3 $end
$var reg 1 % clk $end
$scope module uut $end
$var wire 1 ! a0 $end
$var wire 1 " a1 $end
$var wire 1 # a2 $end
$var wire 1 $ a3 $end
$var wire 1 & clk $end
$var wire 1 ' w1 $end
$scope module D1 $end
$var wire 1 & clk $end
$var wire 1 ' data $end
$var reg 1 ( q $end
$upscope $end
$scope module D2 $end
$var wire 1 & clk $end
$var wire 1 ! data $end
$var reg 1 ) q $end
$upscope $end
$scope module D3 $end
$var wire 1 & clk $end
$var wire 1 " data $end
$var reg 1 * q $end
$upscope $end
$scope module D4 $end
$var wire 1 & clk $end
$var wire 1 # data $end
$var reg 1 + q $end
$upscope $end
$upscope $end
$upscope $end
$enddefinitions $end
#0
$dumpvars
1+
1*
1)
1(
0'
0&
0%
1$
1#
1"
1!
$end
#10
0(
0!
1%
1&
#20
0%
0&
#30
0)
0"
1%
1&
#40
0%
0&
#50
1'
0*
0#
1%
1&
#60
0%
0&
#70
0'
0+
0$
1(
1!
1%
1&
#80
0%
0&
#90
0(
0!
1)
1"
1%
1&
#100
0%
0&
#110
1'
1*
1#
0)
0"
1%
1&
#120
0%
0&
#130
1(
1!
0*
0#
1+
1$
1%
1&
#140
0%
0&
#150
0'
0+
0$
1)
1"
1%
1&
#160
0%
0&
#170
1'
0(
0!
1*
1#
1%
1&
#180
0%
0&
#190
0'
1+
1$
0)
0"
1(
1!
1%
1&
#200
0%
0&
#210
1'
0(
0!
1)
1"
0*
0#
1%
1&
#220
0%
0&
#230
0+
0$
1*
1#
0)
0"
1(
1!
1%
1&
#240
0%
0&
#250
1)
1"
0*
0#
1+
1$
1%
1&
#260
0%
0&
#270
0+
0$
1*
1#
1%
1&
#280
0%
0&
#290
0'
1+
1$
1%
1&
#300
0%
0&
#310
0(
0!
1%
1&
#320
0%
0&
#330
0)
0"
1%
1&
#340
0%
0&
#350
1'
0*
0#
1%
1&
#360
0%
0&
#370
0'
1(
1!
0+
0$
1%
1&
#380
0%
0&
#390
1)
1"
0(
0!
1%
1&
#400
0%
0&
#410
1'
0)
0"
1*
1#
1%
1&
#420
0%
0&
#430
1+
1$
0*
0#
1(
1!
1%
1&
#440
0%
0&
#450
0'
1)
1"
0+
0$
1%
1&
#460
0%
0&
#470
1'
1*
1#
0(
0!
1%
1&
#480
0%
0&
#490
0'
1(
1!
0)
0"
1+
1$
1%
1&
#500
0%
0&
#510
1'
0*
0#
1)
1"
0(
0!
1%
1&
#520
0%
0&
#530
1(
1!
0)
0"
1*
1#
0+
0$
1%
1&
#540
0%
0&
#550
1+
1$
0*
0#
1)
1"
1%
1&
#560
0%
0&
#570
1*
1#
0+
0$
1%
1&
#580
0%
0&
#590
0'
1+
1$
1%
1&
#600
0%
0&
#610
0(
0!
1%
1&
#620
0%
0&
#630
0)
0"
1%
1&
#640
0%
0&
#650
1'
0*
0#
1%
1&
#660
0%
0&
#670
0'
0+
0$
1(
1!
1%
1&
#680
0%
0&
#690
0(
0!
1)
1"
1%
1&
#700
0%
0&
#710
1'
1*
1#
0)
0"
1%
1&
#720
0%
0&
#730
1(
1!
0*
0#
1+
1$
1%
1&
#740
0%
0&
#750
0'
0+
0$
1)
1"
1%
1&
#760
0%
0&
#770
1'
0(
0!
1*
1#
1%
1&
