final-exam/parity/parity.v
module parity(data_in,parity_out);
input [3:0]data_in;
output parity_out;

assign parity_out = (data_in[0] ^ data_in[1]) ^ (data_in[2] ^ data_in[3]);
endmodule

final-exam/parity/parity_tb.v
module parity_tb();
reg [3:0]data_in;
wire parity_out;

parity uut(
	.data_in(data_in),
	.parity_out(parity_out)
	);

initial begin
	data_in = 4'b0000;
	#10 data_in = 4'b1000;
	#10 data_in = 4'b1010;
	#10 data_in = 4'b1011;
	#10 data_in = 4'b0010;
	#10 data_in = 4'b1110;
	#10 data_in = 4'b1111;
	#10 data_in = 4'b1001;
	#10 $finish;
end

initial begin
	$dumpfile("parity.vcd");
	$dumpvars;
end

endmodule

assignments/parity/parity.vcd
$date
	Mon Apr 11 23:17:35 2016
$end
$version
	Icarus Verilog
$end
$timescale
	1s
$end
$scope module parity_tb $end
$var wire 1 ! parity_out $end
$var reg 4 " data_in [3:0] $end
$scope module uut $end
$var wire 4 # data_in [3:0] $end
$var wire 1 ! parity_out $end
$upscope $end
$upscope $end
$enddefinitions $end
#0
$dumpvars
b0 #
b0 "
0!
$end
#10
1!
b1000 "
b1000 #
#20
0!
b1010 "
b1010 #
#30
1!
b1011 "
b1011 #
#40
b10 "
b10 #
#50
b1110 "
b1110 #
#60
0!
b1111 "
b1111 #
#70
b1001 "
b1001 #
