assignments/tffcounter/tffcounter.v
module t_ff(output reg q,input t, rst_n, clk,load,p);
always @ (posedge clk or negedge rst_n)
    if (!rst_n) q <= 1'b0;
	 else if(load) q<=p;
    else if (t) q <= ~q;
endmodule

module counter (output[2:0] q, input rst_n, clk,load,input [2:0] p);
    wire t2;
	 t_ff ff0 ( q[0], 1'b1, rst_n, clk,load,p[0]);
    t_ff ff1 ( q[1], q[0], rst_n, clk,load,p[1]);
    t_ff ff2 ( q[2], t2,   rst_n, clk,load,p[2]);
    and a1 (t2, q[0], q[1]);
    
endmodule

assignments/tffcounter/tffcounter_tb.v
module counter_test;

	// Inputs
	reg rst_n;
	reg clk;
	reg load;
	reg [2:0] p;
	
	wire [2:0] q;

	// Instantiate the Unit Under Test (UUT)
	counter uut (
		.q(q), 
		.rst_n(rst_n), 
		.clk(clk),
		.load(load),
		.p(p)
	);

	initial begin
      clk <= 1'b0;
      forever #5 clk <= ~ clk;
    end
	 
	 initial begin
         load <= 1;
			p=3'b101;
         rst_n <= 1;
			@(posedge clk);
		    load <=0;	
		  repeat (20) @(posedge clk);
		  #0 load<=1;
		  @(posedge clk);
		    load <=0;
			 repeat (10) @(posedge clk);
		  $finish;
    end 

    initial begin
    	$dumpfile("counter.vcd");
    	$dumpvars;
    end 
endmodule

assignments/tffcounter/counter.vcd
$date
	Tue Apr 12 01:28:14 2016
$end
$version
	Icarus Verilog
$end
$timescale
	1s
$end
$scope module counter_test $end
$var wire 3 ! q [2:0] $end
$var reg 1 " clk $end
$var reg 1 # load $end
$var reg 3 $ p [2:0] $end
$var reg 1 % rst_n $end
$scope module uut $end
$var wire 1 & clk $end
$var wire 1 ' load $end
$var wire 3 ( p [2:0] $end
$var wire 3 ) q [2:0] $end
$var wire 1 * rst_n $end
$var wire 1 + t2 $end
$scope module ff0 $end
$var wire 1 & clk $end
$var wire 1 ' load $end
$var wire 1 , p $end
$var wire 1 * rst_n $end
$var wire 1 - t $end
$var reg 1 . q $end
$upscope $end
$scope module ff1 $end
$var wire 1 & clk $end
$var wire 1 ' load $end
$var wire 1 / p $end
$var wire 1 * rst_n $end
$var wire 1 0 t $end
$var reg 1 1 q $end
$upscope $end
$scope module ff2 $end
$var wire 1 & clk $end
$var wire 1 ' load $end
$var wire 1 2 p $end
$var wire 1 * rst_n $end
$var wire 1 + t $end
$var reg 1 3 q $end
$upscope $end
$upscope $end
$upscope $end
$enddefinitions $end
#0
$dumpvars
x3
12
x1
x0
0/
x.
1-
1,
x+
1*
bx )
b101 (
1'
0&
1%
b101 $
1#
0"
bx !
$end
#5
0+
10
1.
01
13
b101 !
b101 )
0#
0'
1"
1&
#10
0"
0&
#15
00
11
0.
b110 !
b110 )
1"
1&
#20
0"
0&
#25
1+
10
1.
b111 !
b111 )
1"
1&
#30
0"
0&
#35
0+
00
03
01
0.
b0 !
b0 )
1"
1&
#40
0"
0&
#45
10
1.
b1 !
b1 )
1"
1&
#50
0"
0&
#55
00
11
0.
b10 !
b10 )
1"
1&
#60
0"
0&
#65
1+
10
1.
b11 !
b11 )
1"
1&
#70
0"
0&
#75
0+
00
13
01
0.
b100 !
b100 )
1"
1&
#80
0"
0&
#85
10
1.
b101 !
b101 )
1"
1&
#90
0"
0&
#95
00
11
0.
b110 !
b110 )
1"
1&
#100
0"
0&
#105
1+
10
1.
b111 !
b111 )
1"
1&
#110
0"
0&
#115
0+
00
03
01
0.
b0 !
b0 )
1"
1&
#120
0"
0&
#125
10
1.
b1 !
b1 )
1"
1&
#130
0"
0&
#135
00
11
0.
b10 !
b10 )
1"
1&
#140
0"
0&
#145
1+
10
1.
b11 !
b11 )
1"
1&
#150
0"
0&
#155
0+
00
13
01
0.
b100 !
b100 )
1"
1&
#160
0"
0&
#165
10
1.
b101 !
b101 )
1"
1&
#170
0"
0&
#175
00
11
0.
b110 !
b110 )
1"
1&
#180
0"
0&
#185
1+
10
1.
b111 !
b111 )
1"
1&
#190
0"
0&
#195
0+
00
03
01
0.
b0 !
b0 )
1"
1&
#200
0"
0&
#205
10
1#
1'
1.
b1 !
b1 )
1"
1&
#210
0"
0&
#215
13
b101 !
b101 )
0#
0'
1"
1&
#220
0"
0&
#225
00
0.
11
b110 !
b110 )
1"
1&
#230
0"
0&
#235
1+
10
1.
b111 !
b111 )
1"
1&
#240
0"
0&
#245
0+
00
0.
01
03
b0 !
b0 )
1"
1&
#250
0"
0&
#255
10
1.
b1 !
b1 )
1"
1&
#260
0"
0&
#265
00
0.
11
b10 !
b10 )
1"
1&
#270
0"
0&
#275
1+
10
1.
b11 !
b11 )
1"
1&
#280
0"
0&
#285
0+
00
0.
01
13
b100 !
b100 )
1"
1&
#290
0"
0&
#295
10
1.
b101 !
b101 )
1"
1&
#300
0"
0&
#305
00
0.
11
b110 !
b110 )
1"
1&
#310
0"
0&
#315
1+
10
1.
b111 !
b111 )
1"
1&
