assignments/mux2to1/mux.v
module mux(m_out,A,B,select);
	input A,B,select;
	output m_out;

	assign m_out = (select) ? A : B;
endmodule

final-exam/mux2to1/mux_tb.v
module mux_tb();

reg A;
reg B;
reg select;

wire m_out;

mux uut(
	.A(A),
	.B(B),
	.select(select),
	.m_out(m_out)
	);

initial begin
	A = 0; B = 0; select = 0;
	#10 A = 1'b0; B = 1'b0; select = 1'b1;
	#10 A = 1'b0; B = 1'b1; select = 1'b0;
	#10 A = 1'b0; B = 1'b1; select = 1'b1;
	#10 A = 1'b1; B = 1'b0; select = 1'b0;
	#10 A = 1'b1; B = 1'b0; select = 1'b1;
	#10 A = 1'b1; B = 1'b1; select = 1'b0;
	#10 A = 1'b1; B = 1'b1; select = 1'b1;
	#10 $finish;
end

initial begin
	$dumpfile("mux.vcd");
	$dumpvars;
end

endmodule

final-exam/mux2to1/mux.vcd
$date
	Mon Apr 11 22:31:08 2016
$end
$version
	Icarus Verilog
$end
$timescale
	1s
$end
$scope module mux_tb $end
$var wire 1 ! m_out $end
$var reg 1 " A $end
$var reg 1 # B $end
$var reg 1 $ select $end
$scope module uut $end
$var wire 1 % A $end
$var wire 1 & B $end
$var wire 1 ! m_out $end
$var wire 1 ' select $end
$upscope $end
$upscope $end
$enddefinitions $end
#0
$dumpvars
0'
0&
0%
0$
0#
0"
0!
$end
#10
1$
1'
#20
1!
0$
0'
1#
1&
#30
0!
1$
1'
#40
0$
0'
0#
0&
1"
1%
#50
1!
1$
1'
#60
0$
0'
1#
1&
#70
1$
1'
