assignments/adder/adder.v
module adder(A,B,Cin,Sum,Cout);
	input A,B,Cin;
	output Sum,Cout;

	assign Sum = A ^ B ^ Cin;
	assign Cout = (Cin & (A^B)) | (A & B);
endmodule

assignments/adder/adder_tb.v
module adder_tb();
	reg A;
	reg B;
	reg Cin;

	wire Sum;
	wire Cout;

	adder uut(
		.A(A),
		.B(B),
		.Cin(Cin),
		.Sum(Sum),
		.Cout(Cout)
	);

	initial begin 
		A = 0;
		B = 0;
		Cin = 0;

		#10 A = 1'b0; B = 1'b1; Cin = 1'b0;
		#10 A = 1'b0; B = 1'b0; Cin = 1'b0;
		#10 A = 1'b1; B = 1'b1; Cin = 1'b1;
		#10 A = 1'b1; B = 1'b0; Cin = 1'b0;
		#10 A = 1'b1; B = 1'b0; Cin = 1'b1;
		#10 A = 1'b0; B = 1'b1; Cin = 1'b1;
		#10 A = 1'b0; B = 1'b0; Cin = 1'b1;
		#10 A = 1'b0; B = 1'b1; Cin = 1'b0;

		#10 $finish;
	end

	initial begin
		$dumpfile("full_adder.vcd");
		$dumpvars;
	end

endmodule

final-exam/adder/full_adder.vcd
$date
	Mon Apr 11 22:06:59 2016
$end
$version
	Icarus Verilog
$end
$timescale
	1s
$end
$scope module adder_tb $end
$var wire 1 ! Cout $end
$var wire 1 " Sum $end
$var reg 1 # A $end
$var reg 1 $ B $end
$var reg 1 % Cin $end
$scope module uut $end
$var wire 1 & A $end
$var wire 1 ' B $end
$var wire 1 ( Cin $end
$var wire 1 ! Cout $end
$var wire 1 " Sum $end
$upscope $end
$upscope $end
$enddefinitions $end
#0
$dumpvars
0(
0'
0&
0%
0$
0#
0"
0!
$end
#10
1"
1$
1'
#20
0"
0$
0'
#30
1!
1"
1%
1(
1$
1'
1#
1&
#40
0!
0%
0(
0$
0'
#50
1!
0"
1%
1(
#60
1$
1'
0#
0&
#70
0!
1"
0$
0'
#80
0%
0(
1$
1'
